MANIFEST.in
README.md
setup.py
ponytools/Allele.py
ponytools/AxiomAnnot.py
ponytools/AxiomCalls.py
ponytools/Exceptions.py
ponytools/MNEcAnnot.py
ponytools/MapPed.py
ponytools/TagSet.py
ponytools/Tools.py
ponytools/Trio.py
ponytools/VCF.py
ponytools/VCFBuffer.py
ponytools/Variant.py
ponytools/__init__.py
ponytools.egg-info/PKG-INFO
ponytools.egg-info/SOURCES.txt
ponytools.egg-info/dependency_links.txt
ponytools.egg-info/requires.txt
ponytools.egg-info/top_level.txt
ponytools/cli/AxiomCalls2VCF.py
ponytools/cli/PR.py
ponytools/cli/VCFInfo.py
ponytools/cli/__init__.py
ponytools/cli/compareVCF.py
ponytools/cli/conform_vcf.py
ponytools/cli/dosageR2.py
ponytools/cli/fastTagger2ldSelect.py
ponytools/cli/impute.py
ponytools/cli/misclassify.py
ponytools/cli/multiPopSelect2tsv.py
ponytools/cli/plotVCFHist.py
ponytools/cli/ponytools
ponytools/cli/pullFastTaggerSNPs.py
ponytools/cli/pyDi.py
ponytools/cli/samples.py
ponytools/cli/sortVCF.py
ponytools/cli/vcf2Di.py
ponytools/cli/vcfRandomSample.py
ponytools/cli/vcf_tools.py
ponytools/data/ImputationMakefile
ponytools/data/MNEc2M_Annotation.csv.gz